<?xml version="1.0" encoding="UTF-8"?>
<modsCollection xmlns:tei="http://www.tei-c.org/ns/1.0"
                xmlns:mods="http://www.loc.gov/mods/v3"
                xmlns="http://www.loc.gov/mods/v3"
                xmlns:xsi="http://www.w3.org/2001/XMLSchema-instance"
                xsi:schemaLocation="http://www.loc.gov/mods/v3 http://www.loc.gov/standards/mods/v3/mods-3-6.xsd">
   <mods ID="oclc_792755362-i_57-div_3.d1e2373-mods">
      <titleInfo>
         <title xml:lang="">في شعرية التصوف: فن الشعر عند الحلاج</title>
      </titleInfo>
      <typeOfResource>text</typeOfResource>
      <genre authority="local" xml:lang="en">journalArticle</genre>
      <genre authority="marcgt" xml:lang="en">article</genre>
      <name type="personal" xml:lang="ar">
         <namePart type="family" xml:lang="ar">سامي علي</namePart>
         <role>
            <roleTerm authority="marcrelator" type="code">aut</roleTerm>
         </role>
      </name>
      <relatedItem type="host">
         <titleInfo>
            <title xml:lang="ar">مواقف</title>
         </titleInfo>
         <genre authority="marcgt">journal</genre>
         <name type="personal" xml:lang="ar">
            <namePart type="family" xml:lang="ar">أدونيس</namePart>
            <role>
               <roleTerm authority="marcrelator" type="code">edt</roleTerm>
            </role>
         </name>
         <originInfo>
            <edition xml:lang="en">digital TEI edition, 2017</edition>
            <place>
               <placeTerm type="text" xml:lang="ar">بيروت</placeTerm>
            </place>
            <dateIssued encoding="w3cdtf">1989</dateIssued>
            <issuance>continuing</issuance>
         </originInfo>
         <part>
            <detail type="volume">
               <number>1989</number>
            </detail>
            <detail type="issue">
               <number>57</number>
            </detail>
            <extent unit="pages">
               <start>10</start>
               <end>17</end>
            </extent>
         </part>
         <identifier type="oclc">792755362</identifier>
         <identifier type="sakhrit">http://archive.sakhrit.co/contents.aspx?CID=15760</identifier>
      </relatedItem>
      <accessCondition>http://creativecommons.org/licenses/by-sa/4.0/</accessCondition>
      <location>
         <url dateLastAccessed="2017-02-21" usage="primary display">https://rawgit.com/tillgrallert/digital-mawaqif/master/xml/oclc_792755362-i_57.TEIP5.xml#div_3.d1e2373</url>
      </location>
      <language>
         <languageTerm type="code"
                       authorityURI="http://www.iana.org/assignments/language-subtag-registry/language-subtag-registry">ar</languageTerm>
      </language>
   </mods>
   <mods ID="oclc_792755362-i_57-div_4.d1e2404-mods">
      <titleInfo>
         <title xml:lang="">همزة الوصل بين السمع والبصر: بول كلي يصغى بعينيه إلى الموسيقى عبر الفن الإسلامي</title>
      </titleInfo>
      <typeOfResource>text</typeOfResource>
      <genre authority="local" xml:lang="en">journalArticle</genre>
      <genre authority="marcgt" xml:lang="en">article</genre>
      <name type="personal" xml:lang="ar">
         <namePart type="family" xml:lang="ar">أسعد عرابي</namePart>
         <role>
            <roleTerm authority="marcrelator" type="code">aut</roleTerm>
         </role>
      </name>
      <relatedItem type="host">
         <titleInfo>
            <title xml:lang="ar">مواقف</title>
         </titleInfo>
         <genre authority="marcgt">journal</genre>
         <name type="personal" xml:lang="ar">
            <namePart type="family" xml:lang="ar">أدونيس</namePart>
            <role>
               <roleTerm authority="marcrelator" type="code">edt</roleTerm>
            </role>
         </name>
         <originInfo>
            <edition xml:lang="en">digital TEI edition, 2017</edition>
            <place>
               <placeTerm type="text" xml:lang="ar">بيروت</placeTerm>
            </place>
            <dateIssued encoding="w3cdtf">1989</dateIssued>
            <issuance>continuing</issuance>
         </originInfo>
         <part>
            <detail type="volume">
               <number>1989</number>
            </detail>
            <detail type="issue">
               <number>57</number>
            </detail>
            <extent unit="pages">
               <start>18</start>
               <end>29</end>
            </extent>
         </part>
         <identifier type="oclc">792755362</identifier>
         <identifier type="sakhrit">http://archive.sakhrit.co/contents.aspx?CID=15760</identifier>
      </relatedItem>
      <accessCondition>http://creativecommons.org/licenses/by-sa/4.0/</accessCondition>
      <location>
         <url dateLastAccessed="2017-02-21" usage="primary display">https://rawgit.com/tillgrallert/digital-mawaqif/master/xml/oclc_792755362-i_57.TEIP5.xml#div_4.d1e2404</url>
      </location>
      <language>
         <languageTerm type="code"
                       authorityURI="http://www.iana.org/assignments/language-subtag-registry/language-subtag-registry">ar</languageTerm>
      </language>
   </mods>
   <mods ID="oclc_792755362-i_57-div_5.d1e2445-mods">
      <titleInfo>
         <title xml:lang="">رامبو، مشرقيا، صوفيا</title>
      </titleInfo>
      <typeOfResource>text</typeOfResource>
      <genre authority="local" xml:lang="en">journalArticle</genre>
      <genre authority="marcgt" xml:lang="en">article</genre>
      <name type="personal" xml:lang="ar">
         <namePart type="family" xml:lang="ar">علي أحمد سعيد إسبر (أدونيس)</namePart>
         <role>
            <roleTerm authority="marcrelator" type="code">aut</roleTerm>
         </role>
      </name>
      <relatedItem type="host">
         <titleInfo>
            <title xml:lang="ar">مواقف</title>
         </titleInfo>
         <genre authority="marcgt">journal</genre>
         <name type="personal" xml:lang="ar">
            <namePart type="family" xml:lang="ar">أدونيس</namePart>
            <role>
               <roleTerm authority="marcrelator" type="code">edt</roleTerm>
            </role>
         </name>
         <originInfo>
            <edition xml:lang="en">digital TEI edition, 2017</edition>
            <place>
               <placeTerm type="text" xml:lang="ar">بيروت</placeTerm>
            </place>
            <dateIssued encoding="w3cdtf">1989</dateIssued>
            <issuance>continuing</issuance>
         </originInfo>
         <part>
            <detail type="volume">
               <number>1989</number>
            </detail>
            <detail type="issue">
               <number>57</number>
            </detail>
            <extent unit="pages">
               <start>30</start>
               <end>45</end>
            </extent>
         </part>
         <identifier type="oclc">792755362</identifier>
         <identifier type="sakhrit">http://archive.sakhrit.co/contents.aspx?CID=15760</identifier>
      </relatedItem>
      <accessCondition>http://creativecommons.org/licenses/by-sa/4.0/</accessCondition>
      <location>
         <url dateLastAccessed="2017-02-21" usage="primary display">https://rawgit.com/tillgrallert/digital-mawaqif/master/xml/oclc_792755362-i_57.TEIP5.xml#div_5.d1e2445</url>
      </location>
      <language>
         <languageTerm type="code"
                       authorityURI="http://www.iana.org/assignments/language-subtag-registry/language-subtag-registry">ar</languageTerm>
      </language>
   </mods>
   <mods ID="oclc_792755362-i_57-div_6.d1e2494-mods">
      <titleInfo>
         <title xml:lang="">جنائن يضيئها الهذيان</title>
      </titleInfo>
      <typeOfResource>text</typeOfResource>
      <genre authority="local" xml:lang="en">journalArticle</genre>
      <genre authority="marcgt" xml:lang="en">article</genre>
      <name type="personal" xml:lang="ar">
         <namePart type="family" xml:lang="ar">وساط مبارك</namePart>
         <role>
            <roleTerm authority="marcrelator" type="code">aut</roleTerm>
         </role>
      </name>
      <relatedItem type="host">
         <titleInfo>
            <title xml:lang="ar">مواقف</title>
         </titleInfo>
         <genre authority="marcgt">journal</genre>
         <name type="personal" xml:lang="ar">
            <namePart type="family" xml:lang="ar">أدونيس</namePart>
            <role>
               <roleTerm authority="marcrelator" type="code">edt</roleTerm>
            </role>
         </name>
         <originInfo>
            <edition xml:lang="en">digital TEI edition, 2017</edition>
            <place>
               <placeTerm type="text" xml:lang="ar">بيروت</placeTerm>
            </place>
            <dateIssued encoding="w3cdtf">1989</dateIssued>
            <issuance>continuing</issuance>
         </originInfo>
         <part>
            <detail type="volume">
               <number>1989</number>
            </detail>
            <detail type="issue">
               <number>57</number>
            </detail>
            <extent unit="pages">
               <start>46</start>
               <end>50</end>
            </extent>
         </part>
         <identifier type="oclc">792755362</identifier>
         <identifier type="sakhrit">http://archive.sakhrit.co/contents.aspx?CID=15760</identifier>
      </relatedItem>
      <accessCondition>http://creativecommons.org/licenses/by-sa/4.0/</accessCondition>
      <location>
         <url dateLastAccessed="2017-02-21" usage="primary display">https://rawgit.com/tillgrallert/digital-mawaqif/master/xml/oclc_792755362-i_57.TEIP5.xml#div_6.d1e2494</url>
      </location>
      <language>
         <languageTerm type="code"
                       authorityURI="http://www.iana.org/assignments/language-subtag-registry/language-subtag-registry">ar</languageTerm>
      </language>
   </mods>
   <mods ID="oclc_792755362-i_57-div_7.d1e2519-mods">
      <titleInfo>
         <title xml:lang="">أوقات مع ميرو</title>
      </titleInfo>
      <typeOfResource>text</typeOfResource>
      <genre authority="local" xml:lang="en">journalArticle</genre>
      <genre authority="marcgt" xml:lang="en">article</genre>
      <name type="personal" xml:lang="ar">
         <namePart type="family" xml:lang="ar">جمال جمعة</namePart>
         <role>
            <roleTerm authority="marcrelator" type="code">aut</roleTerm>
         </role>
      </name>
      <relatedItem type="host">
         <titleInfo>
            <title xml:lang="ar">مواقف</title>
         </titleInfo>
         <genre authority="marcgt">journal</genre>
         <name type="personal" xml:lang="ar">
            <namePart type="family" xml:lang="ar">أدونيس</namePart>
            <role>
               <roleTerm authority="marcrelator" type="code">edt</roleTerm>
            </role>
         </name>
         <originInfo>
            <edition xml:lang="en">digital TEI edition, 2017</edition>
            <place>
               <placeTerm type="text" xml:lang="ar">بيروت</placeTerm>
            </place>
            <dateIssued encoding="w3cdtf">1989</dateIssued>
            <issuance>continuing</issuance>
         </originInfo>
         <part>
            <detail type="volume">
               <number>1989</number>
            </detail>
            <detail type="issue">
               <number>57</number>
            </detail>
            <extent unit="pages">
               <start>51</start>
               <end>62</end>
            </extent>
         </part>
         <identifier type="oclc">792755362</identifier>
         <identifier type="sakhrit">http://archive.sakhrit.co/contents.aspx?CID=15760</identifier>
      </relatedItem>
      <accessCondition>http://creativecommons.org/licenses/by-sa/4.0/</accessCondition>
      <location>
         <url dateLastAccessed="2017-02-21" usage="primary display">https://rawgit.com/tillgrallert/digital-mawaqif/master/xml/oclc_792755362-i_57.TEIP5.xml#div_7.d1e2519</url>
      </location>
      <language>
         <languageTerm type="code"
                       authorityURI="http://www.iana.org/assignments/language-subtag-registry/language-subtag-registry">ar</languageTerm>
      </language>
   </mods>
   <mods ID="oclc_792755362-i_57-div_8.d1e2560-mods">
      <titleInfo>
         <title xml:lang="">وحياتي تستمر</title>
      </titleInfo>
      <typeOfResource>text</typeOfResource>
      <genre authority="local" xml:lang="en">journalArticle</genre>
      <genre authority="marcgt" xml:lang="en">article</genre>
      <name type="personal" xml:lang="ar">
         <namePart type="family" xml:lang="ar">فدوى طوقان</namePart>
         <role>
            <roleTerm authority="marcrelator" type="code">aut</roleTerm>
         </role>
      </name>
      <relatedItem type="host">
         <titleInfo>
            <title xml:lang="ar">مواقف</title>
         </titleInfo>
         <genre authority="marcgt">journal</genre>
         <name type="personal" xml:lang="ar">
            <namePart type="family" xml:lang="ar">أدونيس</namePart>
            <role>
               <roleTerm authority="marcrelator" type="code">edt</roleTerm>
            </role>
         </name>
         <originInfo>
            <edition xml:lang="en">digital TEI edition, 2017</edition>
            <place>
               <placeTerm type="text" xml:lang="ar">بيروت</placeTerm>
            </place>
            <dateIssued encoding="w3cdtf">1989</dateIssued>
            <issuance>continuing</issuance>
         </originInfo>
         <part>
            <detail type="volume">
               <number>1989</number>
            </detail>
            <detail type="issue">
               <number>57</number>
            </detail>
            <extent unit="pages">
               <start>63</start>
               <end>67</end>
            </extent>
         </part>
         <identifier type="oclc">792755362</identifier>
         <identifier type="sakhrit">http://archive.sakhrit.co/contents.aspx?CID=15760</identifier>
      </relatedItem>
      <accessCondition>http://creativecommons.org/licenses/by-sa/4.0/</accessCondition>
      <location>
         <url dateLastAccessed="2017-02-21" usage="primary display">https://rawgit.com/tillgrallert/digital-mawaqif/master/xml/oclc_792755362-i_57.TEIP5.xml#div_8.d1e2560</url>
      </location>
      <language>
         <languageTerm type="code"
                       authorityURI="http://www.iana.org/assignments/language-subtag-registry/language-subtag-registry">ar</languageTerm>
      </language>
   </mods>
   <mods ID="oclc_792755362-i_57-div_9.d1e2585-mods">
      <titleInfo>
         <title xml:lang="">تأملات / حجارة</title>
      </titleInfo>
      <typeOfResource>text</typeOfResource>
      <genre authority="local" xml:lang="en">journalArticle</genre>
      <genre authority="marcgt" xml:lang="en">article</genre>
      <name type="personal" xml:lang="ar">
         <namePart type="family" xml:lang="ar">منى السعودي</namePart>
         <role>
            <roleTerm authority="marcrelator" type="code">aut</roleTerm>
         </role>
      </name>
      <relatedItem type="host">
         <titleInfo>
            <title xml:lang="ar">مواقف</title>
         </titleInfo>
         <genre authority="marcgt">journal</genre>
         <name type="personal" xml:lang="ar">
            <namePart type="family" xml:lang="ar">أدونيس</namePart>
            <role>
               <roleTerm authority="marcrelator" type="code">edt</roleTerm>
            </role>
         </name>
         <originInfo>
            <edition xml:lang="en">digital TEI edition, 2017</edition>
            <place>
               <placeTerm type="text" xml:lang="ar">بيروت</placeTerm>
            </place>
            <dateIssued encoding="w3cdtf">1989</dateIssued>
            <issuance>continuing</issuance>
         </originInfo>
         <part>
            <detail type="volume">
               <number>1989</number>
            </detail>
            <detail type="issue">
               <number>57</number>
            </detail>
            <extent unit="pages">
               <start>68</start>
               <end>72</end>
            </extent>
         </part>
         <identifier type="oclc">792755362</identifier>
         <identifier type="sakhrit">http://archive.sakhrit.co/contents.aspx?CID=15760</identifier>
      </relatedItem>
      <accessCondition>http://creativecommons.org/licenses/by-sa/4.0/</accessCondition>
      <location>
         <url dateLastAccessed="2017-02-21" usage="primary display">https://rawgit.com/tillgrallert/digital-mawaqif/master/xml/oclc_792755362-i_57.TEIP5.xml#div_9.d1e2585</url>
      </location>
      <language>
         <languageTerm type="code"
                       authorityURI="http://www.iana.org/assignments/language-subtag-registry/language-subtag-registry">ar</languageTerm>
      </language>
   </mods>
   <mods ID="oclc_792755362-i_57-div_10.d1e2610-mods">
      <titleInfo>
         <title xml:lang="">ثماني قصائد</title>
      </titleInfo>
      <typeOfResource>text</typeOfResource>
      <genre authority="local" xml:lang="en">journalArticle</genre>
      <genre authority="marcgt" xml:lang="en">article</genre>
      <name type="personal" xml:lang="ar">
         <namePart type="family" xml:lang="ar">إنجمار ليكبوس</namePart>
         <role>
            <roleTerm authority="marcrelator" type="code">aut</roleTerm>
         </role>
      </name>
      <relatedItem type="host">
         <titleInfo>
            <title xml:lang="ar">مواقف</title>
         </titleInfo>
         <genre authority="marcgt">journal</genre>
         <name type="personal" xml:lang="ar">
            <namePart type="family" xml:lang="ar">أدونيس</namePart>
            <role>
               <roleTerm authority="marcrelator" type="code">edt</roleTerm>
            </role>
         </name>
         <originInfo>
            <edition xml:lang="en">digital TEI edition, 2017</edition>
            <place>
               <placeTerm type="text" xml:lang="ar">بيروت</placeTerm>
            </place>
            <dateIssued encoding="w3cdtf">1989</dateIssued>
            <issuance>continuing</issuance>
         </originInfo>
         <part>
            <detail type="volume">
               <number>1989</number>
            </detail>
            <detail type="issue">
               <number>57</number>
            </detail>
            <extent unit="pages">
               <start>73</start>
               <end>81</end>
            </extent>
         </part>
         <identifier type="oclc">792755362</identifier>
         <identifier type="sakhrit">http://archive.sakhrit.co/contents.aspx?CID=15760</identifier>
      </relatedItem>
      <accessCondition>http://creativecommons.org/licenses/by-sa/4.0/</accessCondition>
      <location>
         <url dateLastAccessed="2017-02-21" usage="primary display">https://rawgit.com/tillgrallert/digital-mawaqif/master/xml/oclc_792755362-i_57.TEIP5.xml#div_10.d1e2610</url>
      </location>
      <language>
         <languageTerm type="code"
                       authorityURI="http://www.iana.org/assignments/language-subtag-registry/language-subtag-registry">ar</languageTerm>
      </language>
   </mods>
   <mods ID="oclc_792755362-i_57-div_11.d1e2644-mods">
      <titleInfo>
         <title xml:lang="">تسع قصائد</title>
      </titleInfo>
      <typeOfResource>text</typeOfResource>
      <genre authority="local" xml:lang="en">journalArticle</genre>
      <genre authority="marcgt" xml:lang="en">article</genre>
      <name type="personal" xml:lang="ar">
         <namePart type="family" xml:lang="ar">أندريه فيلتر</namePart>
         <role>
            <roleTerm authority="marcrelator" type="code">aut</roleTerm>
         </role>
      </name>
      <relatedItem type="host">
         <titleInfo>
            <title xml:lang="ar">مواقف</title>
         </titleInfo>
         <genre authority="marcgt">journal</genre>
         <name type="personal" xml:lang="ar">
            <namePart type="family" xml:lang="ar">أدونيس</namePart>
            <role>
               <roleTerm authority="marcrelator" type="code">edt</roleTerm>
            </role>
         </name>
         <originInfo>
            <edition xml:lang="en">digital TEI edition, 2017</edition>
            <place>
               <placeTerm type="text" xml:lang="ar">بيروت</placeTerm>
            </place>
            <dateIssued encoding="w3cdtf">1989</dateIssued>
            <issuance>continuing</issuance>
         </originInfo>
         <part>
            <detail type="volume">
               <number>1989</number>
            </detail>
            <detail type="issue">
               <number>57</number>
            </detail>
            <extent unit="pages">
               <start>82</start>
               <end>91</end>
            </extent>
         </part>
         <identifier type="oclc">792755362</identifier>
         <identifier type="sakhrit">http://archive.sakhrit.co/contents.aspx?CID=15760</identifier>
      </relatedItem>
      <accessCondition>http://creativecommons.org/licenses/by-sa/4.0/</accessCondition>
      <location>
         <url dateLastAccessed="2017-02-21" usage="primary display">https://rawgit.com/tillgrallert/digital-mawaqif/master/xml/oclc_792755362-i_57.TEIP5.xml#div_11.d1e2644</url>
      </location>
      <language>
         <languageTerm type="code"
                       authorityURI="http://www.iana.org/assignments/language-subtag-registry/language-subtag-registry">ar</languageTerm>
      </language>
   </mods>
   <mods ID="oclc_792755362-i_57-div_12.d1e2680-mods">
      <titleInfo>
         <title xml:lang="">الأصوات الثلاثة في الشعر العربي المعاصر: دراسة تطبيقية</title>
      </titleInfo>
      <typeOfResource>text</typeOfResource>
      <genre authority="local" xml:lang="en">journalArticle</genre>
      <genre authority="marcgt" xml:lang="en">article</genre>
      <name type="personal" xml:lang="ar">
         <namePart type="family" xml:lang="ar">عبد العزيز المقالح</namePart>
         <role>
            <roleTerm authority="marcrelator" type="code">aut</roleTerm>
         </role>
      </name>
      <relatedItem type="host">
         <titleInfo>
            <title xml:lang="ar">مواقف</title>
         </titleInfo>
         <genre authority="marcgt">journal</genre>
         <name type="personal" xml:lang="ar">
            <namePart type="family" xml:lang="ar">أدونيس</namePart>
            <role>
               <roleTerm authority="marcrelator" type="code">edt</roleTerm>
            </role>
         </name>
         <originInfo>
            <edition xml:lang="en">digital TEI edition, 2017</edition>
            <place>
               <placeTerm type="text" xml:lang="ar">بيروت</placeTerm>
            </place>
            <dateIssued encoding="w3cdtf">1989</dateIssued>
            <issuance>continuing</issuance>
         </originInfo>
         <part>
            <detail type="volume">
               <number>1989</number>
            </detail>
            <detail type="issue">
               <number>57</number>
            </detail>
            <extent unit="pages">
               <start>92</start>
               <end>118</end>
            </extent>
         </part>
         <identifier type="oclc">792755362</identifier>
         <identifier type="sakhrit">http://archive.sakhrit.co/contents.aspx?CID=15760</identifier>
      </relatedItem>
      <accessCondition>http://creativecommons.org/licenses/by-sa/4.0/</accessCondition>
      <location>
         <url dateLastAccessed="2017-02-21" usage="primary display">https://rawgit.com/tillgrallert/digital-mawaqif/master/xml/oclc_792755362-i_57.TEIP5.xml#div_12.d1e2680</url>
      </location>
      <language>
         <languageTerm type="code"
                       authorityURI="http://www.iana.org/assignments/language-subtag-registry/language-subtag-registry">ar</languageTerm>
      </language>
   </mods>
   <mods ID="oclc_792755362-i_57-div_13.d1e2752-mods">
      <titleInfo>
         <title xml:lang="">خواطر حول وأد الإبداع</title>
      </titleInfo>
      <typeOfResource>text</typeOfResource>
      <genre authority="local" xml:lang="en">journalArticle</genre>
      <genre authority="marcgt" xml:lang="en">article</genre>
      <name type="personal" xml:lang="ar">
         <namePart type="family" xml:lang="ar">طارق حسن علي</namePart>
         <role>
            <roleTerm authority="marcrelator" type="code">aut</roleTerm>
         </role>
      </name>
      <relatedItem type="host">
         <titleInfo>
            <title xml:lang="ar">مواقف</title>
         </titleInfo>
         <genre authority="marcgt">journal</genre>
         <name type="personal" xml:lang="ar">
            <namePart type="family" xml:lang="ar">أدونيس</namePart>
            <role>
               <roleTerm authority="marcrelator" type="code">edt</roleTerm>
            </role>
         </name>
         <originInfo>
            <edition xml:lang="en">digital TEI edition, 2017</edition>
            <place>
               <placeTerm type="text" xml:lang="ar">بيروت</placeTerm>
            </place>
            <dateIssued encoding="w3cdtf">1989</dateIssued>
            <issuance>continuing</issuance>
         </originInfo>
         <part>
            <detail type="volume">
               <number>1989</number>
            </detail>
            <detail type="issue">
               <number>57</number>
            </detail>
            <extent unit="pages">
               <start>119</start>
               <end>128</end>
            </extent>
         </part>
         <identifier type="oclc">792755362</identifier>
         <identifier type="sakhrit">http://archive.sakhrit.co/contents.aspx?CID=15760</identifier>
      </relatedItem>
      <accessCondition>http://creativecommons.org/licenses/by-sa/4.0/</accessCondition>
      <location>
         <url dateLastAccessed="2017-02-21" usage="primary display">https://rawgit.com/tillgrallert/digital-mawaqif/master/xml/oclc_792755362-i_57.TEIP5.xml#div_13.d1e2752</url>
      </location>
      <language>
         <languageTerm type="code"
                       authorityURI="http://www.iana.org/assignments/language-subtag-registry/language-subtag-registry">ar</languageTerm>
      </language>
   </mods>
   <mods ID="oclc_792755362-i_57-div_14.d1e2789-mods">
      <titleInfo>
         <title xml:lang="">الجبل الصغير بديل مكان</title>
      </titleInfo>
      <typeOfResource>text</typeOfResource>
      <genre authority="local" xml:lang="en">journalArticle</genre>
      <genre authority="marcgt" xml:lang="en">article</genre>
      <name type="personal" xml:lang="ar">
         <namePart type="family" xml:lang="ar">صباح خ . زوبن</namePart>
         <role>
            <roleTerm authority="marcrelator" type="code">aut</roleTerm>
         </role>
      </name>
      <relatedItem type="host">
         <titleInfo>
            <title xml:lang="ar">مواقف</title>
         </titleInfo>
         <genre authority="marcgt">journal</genre>
         <name type="personal" xml:lang="ar">
            <namePart type="family" xml:lang="ar">أدونيس</namePart>
            <role>
               <roleTerm authority="marcrelator" type="code">edt</roleTerm>
            </role>
         </name>
         <originInfo>
            <edition xml:lang="en">digital TEI edition, 2017</edition>
            <place>
               <placeTerm type="text" xml:lang="ar">بيروت</placeTerm>
            </place>
            <dateIssued encoding="w3cdtf">1989</dateIssued>
            <issuance>continuing</issuance>
         </originInfo>
         <part>
            <detail type="volume">
               <number>1989</number>
            </detail>
            <detail type="issue">
               <number>57</number>
            </detail>
            <extent unit="pages">
               <start>129</start>
               <end>131</end>
            </extent>
         </part>
         <identifier type="oclc">792755362</identifier>
         <identifier type="sakhrit">http://archive.sakhrit.co/contents.aspx?CID=15760</identifier>
      </relatedItem>
      <accessCondition>http://creativecommons.org/licenses/by-sa/4.0/</accessCondition>
      <location>
         <url dateLastAccessed="2017-02-21" usage="primary display">https://rawgit.com/tillgrallert/digital-mawaqif/master/xml/oclc_792755362-i_57.TEIP5.xml#div_14.d1e2789</url>
      </location>
      <language>
         <languageTerm type="code"
                       authorityURI="http://www.iana.org/assignments/language-subtag-registry/language-subtag-registry">ar</languageTerm>
      </language>
   </mods>
   <mods ID="oclc_792755362-i_57-div_15.d1e2809-mods">
      <titleInfo>
         <title xml:lang="">قداس لراحة القديس والشهيد جان جينيه</title>
      </titleInfo>
      <typeOfResource>text</typeOfResource>
      <genre authority="local" xml:lang="en">journalArticle</genre>
      <genre authority="marcgt" xml:lang="en">article</genre>
      <name type="personal" xml:lang="ar">
         <namePart type="family" xml:lang="ar">المعطي قبال</namePart>
         <role>
            <roleTerm authority="marcrelator" type="code">aut</roleTerm>
         </role>
      </name>
      <relatedItem type="host">
         <titleInfo>
            <title xml:lang="ar">مواقف</title>
         </titleInfo>
         <genre authority="marcgt">journal</genre>
         <name type="personal" xml:lang="ar">
            <namePart type="family" xml:lang="ar">أدونيس</namePart>
            <role>
               <roleTerm authority="marcrelator" type="code">edt</roleTerm>
            </role>
         </name>
         <originInfo>
            <edition xml:lang="en">digital TEI edition, 2017</edition>
            <place>
               <placeTerm type="text" xml:lang="ar">بيروت</placeTerm>
            </place>
            <dateIssued encoding="w3cdtf">1989</dateIssued>
            <issuance>continuing</issuance>
         </originInfo>
         <part>
            <detail type="volume">
               <number>1989</number>
            </detail>
            <detail type="issue">
               <number>57</number>
            </detail>
            <extent unit="pages">
               <start>132</start>
               <end>137</end>
            </extent>
         </part>
         <identifier type="oclc">792755362</identifier>
         <identifier type="sakhrit">http://archive.sakhrit.co/contents.aspx?CID=15760</identifier>
      </relatedItem>
      <accessCondition>http://creativecommons.org/licenses/by-sa/4.0/</accessCondition>
      <location>
         <url dateLastAccessed="2017-02-21" usage="primary display">https://rawgit.com/tillgrallert/digital-mawaqif/master/xml/oclc_792755362-i_57.TEIP5.xml#div_15.d1e2809</url>
      </location>
      <language>
         <languageTerm type="code"
                       authorityURI="http://www.iana.org/assignments/language-subtag-registry/language-subtag-registry">ar</languageTerm>
      </language>
   </mods>
   <mods ID="oclc_792755362-i_57-div_16.d1e2836-mods">
      <titleInfo>
         <title xml:lang="">المثقفون والسلطة: حوار بين ميشيل فوكو وجيل دولوز</title>
      </titleInfo>
      <typeOfResource>text</typeOfResource>
      <genre authority="local" xml:lang="en">journalArticle</genre>
      <genre authority="marcgt" xml:lang="en">article</genre>
      <name type="personal" xml:lang="ar">
         <namePart type="family" xml:lang="ar">حسين عجة</namePart>
         <role>
            <roleTerm authority="marcrelator" type="code">aut</roleTerm>
         </role>
      </name>
      <relatedItem type="host">
         <titleInfo>
            <title xml:lang="ar">مواقف</title>
         </titleInfo>
         <genre authority="marcgt">journal</genre>
         <name type="personal" xml:lang="ar">
            <namePart type="family" xml:lang="ar">أدونيس</namePart>
            <role>
               <roleTerm authority="marcrelator" type="code">edt</roleTerm>
            </role>
         </name>
         <originInfo>
            <edition xml:lang="en">digital TEI edition, 2017</edition>
            <place>
               <placeTerm type="text" xml:lang="ar">بيروت</placeTerm>
            </place>
            <dateIssued encoding="w3cdtf">1989</dateIssued>
            <issuance>continuing</issuance>
         </originInfo>
         <part>
            <detail type="volume">
               <number>1989</number>
            </detail>
            <detail type="issue">
               <number>57</number>
            </detail>
            <extent unit="pages">
               <start>138</start>
               <end>147</end>
            </extent>
         </part>
         <identifier type="oclc">792755362</identifier>
         <identifier type="sakhrit">http://archive.sakhrit.co/contents.aspx?CID=15760</identifier>
      </relatedItem>
      <accessCondition>http://creativecommons.org/licenses/by-sa/4.0/</accessCondition>
      <location>
         <url dateLastAccessed="2017-02-21" usage="primary display">https://rawgit.com/tillgrallert/digital-mawaqif/master/xml/oclc_792755362-i_57.TEIP5.xml#div_16.d1e2836</url>
      </location>
      <language>
         <languageTerm type="code"
                       authorityURI="http://www.iana.org/assignments/language-subtag-registry/language-subtag-registry">ar</languageTerm>
      </language>
   </mods>
   <mods ID="oclc_792755362-i_57-div_17.d1e2873-mods">
      <titleInfo>
         <title xml:lang="">سبق نفسه ومضى دون هدف</title>
      </titleInfo>
      <typeOfResource>text</typeOfResource>
      <genre authority="local" xml:lang="en">journalArticle</genre>
      <genre authority="marcgt" xml:lang="en">article</genre>
      <name type="personal" xml:lang="ar">
         <namePart type="family" xml:lang="ar">صمويل بيكيت</namePart>
         <role>
            <roleTerm authority="marcrelator" type="code">aut</roleTerm>
         </role>
      </name>
      <relatedItem type="host">
         <titleInfo>
            <title xml:lang="ar">مواقف</title>
         </titleInfo>
         <genre authority="marcgt">journal</genre>
         <name type="personal" xml:lang="ar">
            <namePart type="family" xml:lang="ar">أدونيس</namePart>
            <role>
               <roleTerm authority="marcrelator" type="code">edt</roleTerm>
            </role>
         </name>
         <originInfo>
            <edition xml:lang="en">digital TEI edition, 2017</edition>
            <place>
               <placeTerm type="text" xml:lang="ar">بيروت</placeTerm>
            </place>
            <dateIssued encoding="w3cdtf">1989</dateIssued>
            <issuance>continuing</issuance>
         </originInfo>
         <part>
            <detail type="volume">
               <number>1989</number>
            </detail>
            <detail type="issue">
               <number>57</number>
            </detail>
            <extent unit="pages">
               <start>148</start>
               <end>163</end>
            </extent>
         </part>
         <identifier type="oclc">792755362</identifier>
         <identifier type="sakhrit">http://archive.sakhrit.co/contents.aspx?CID=15760</identifier>
      </relatedItem>
      <accessCondition>http://creativecommons.org/licenses/by-sa/4.0/</accessCondition>
      <location>
         <url dateLastAccessed="2017-02-21" usage="primary display">https://rawgit.com/tillgrallert/digital-mawaqif/master/xml/oclc_792755362-i_57.TEIP5.xml#div_17.d1e2873</url>
      </location>
      <language>
         <languageTerm type="code"
                       authorityURI="http://www.iana.org/assignments/language-subtag-registry/language-subtag-registry">ar</languageTerm>
      </language>
   </mods>
   <mods ID="oclc_792755362-i_57-div_18.d1e2922-mods">
      <titleInfo>
         <title xml:lang="">نجيب محفوظ العربي الأول</title>
      </titleInfo>
      <typeOfResource>text</typeOfResource>
      <genre authority="local" xml:lang="en">journalArticle</genre>
      <genre authority="marcgt" xml:lang="en">article</genre>
      <name type="personal" xml:lang="ar">
         <namePart type="family" xml:lang="ar">إلياس خوري</namePart>
         <role>
            <roleTerm authority="marcrelator" type="code">aut</roleTerm>
         </role>
      </name>
      <relatedItem type="host">
         <titleInfo>
            <title xml:lang="ar">مواقف</title>
         </titleInfo>
         <genre authority="marcgt">journal</genre>
         <name type="personal" xml:lang="ar">
            <namePart type="family" xml:lang="ar">أدونيس</namePart>
            <role>
               <roleTerm authority="marcrelator" type="code">edt</roleTerm>
            </role>
         </name>
         <originInfo>
            <edition xml:lang="en">digital TEI edition, 2017</edition>
            <place>
               <placeTerm type="text" xml:lang="ar">بيروت</placeTerm>
            </place>
            <dateIssued encoding="w3cdtf">1989</dateIssued>
            <issuance>continuing</issuance>
         </originInfo>
         <part>
            <detail type="volume">
               <number>1989</number>
            </detail>
            <detail type="issue">
               <number>57</number>
            </detail>
            <extent unit="pages">
               <start>164</start>
               <end>168</end>
            </extent>
         </part>
         <identifier type="oclc">792755362</identifier>
         <identifier type="sakhrit">http://archive.sakhrit.co/contents.aspx?CID=15760</identifier>
      </relatedItem>
      <accessCondition>http://creativecommons.org/licenses/by-sa/4.0/</accessCondition>
      <location>
         <url dateLastAccessed="2017-02-21" usage="primary display">https://rawgit.com/tillgrallert/digital-mawaqif/master/xml/oclc_792755362-i_57.TEIP5.xml#div_18.d1e2922</url>
      </location>
      <language>
         <languageTerm type="code"
                       authorityURI="http://www.iana.org/assignments/language-subtag-registry/language-subtag-registry">ar</languageTerm>
      </language>
   </mods>
   <mods ID="oclc_792755362-i_57-div_19.d1e2947-mods">
      <titleInfo>
         <title xml:lang="">أحلم وأطيع آية الشمس</title>
      </titleInfo>
      <typeOfResource>text</typeOfResource>
      <genre authority="local" xml:lang="en">journalArticle</genre>
      <genre authority="marcgt" xml:lang="en">article</genre>
      <name type="personal" xml:lang="ar">
         <namePart type="family" xml:lang="ar">علي أحمد سعيد إسبر (أدونيس)</namePart>
         <role>
            <roleTerm authority="marcrelator" type="code">aut</roleTerm>
         </role>
      </name>
      <relatedItem type="host">
         <titleInfo>
            <title xml:lang="ar">مواقف</title>
         </titleInfo>
         <genre authority="marcgt">journal</genre>
         <name type="personal" xml:lang="ar">
            <namePart type="family" xml:lang="ar">أدونيس</namePart>
            <role>
               <roleTerm authority="marcrelator" type="code">edt</roleTerm>
            </role>
         </name>
         <originInfo>
            <edition xml:lang="en">digital TEI edition, 2017</edition>
            <place>
               <placeTerm type="text" xml:lang="ar">بيروت</placeTerm>
            </place>
            <dateIssued encoding="w3cdtf">1989</dateIssued>
            <issuance>continuing</issuance>
         </originInfo>
         <part>
            <detail type="volume">
               <number>1989</number>
            </detail>
            <detail type="issue">
               <number>57</number>
            </detail>
            <extent unit="pages">
               <start>169</start>
               <end>169</end>
            </extent>
         </part>
         <identifier type="oclc">792755362</identifier>
         <identifier type="sakhrit">http://archive.sakhrit.co/contents.aspx?CID=15760</identifier>
      </relatedItem>
      <accessCondition>http://creativecommons.org/licenses/by-sa/4.0/</accessCondition>
      <location>
         <url dateLastAccessed="2017-02-21" usage="primary display">https://rawgit.com/tillgrallert/digital-mawaqif/master/xml/oclc_792755362-i_57.TEIP5.xml#div_19.d1e2947</url>
      </location>
      <language>
         <languageTerm type="code"
                       authorityURI="http://www.iana.org/assignments/language-subtag-registry/language-subtag-registry">ar</languageTerm>
      </language>
   </mods>
</modsCollection>
